pelican/plugins/image_process/__init__.py
pelican/plugins/image_process/image_process.py
pelican/plugins/image_process/test_data/alpha-borders.png
pelican/plugins/image_process/test_data/alpha-borders.webp
pelican/plugins/image_process/test_data/black-borders.png
pelican/plugins/image_process/test_data/exif/pelican-bird.jpg
pelican/plugins/image_process/test_data/exif/pelican-bird.png
pelican/plugins/image_process/test_data/folded_puzzle.png
pelican/plugins/image_process/test_data/minimal.svg
pelican/plugins/image_process/test_data/noexif/pelican-bird.jpg
pelican/plugins/image_process/test_data/noexif/pelican-bird.png
pelican/plugins/image_process/test_data/pelican-bird.jpg
pelican/plugins/image_process/test_data/pelican-bird.png
pelican/plugins/image_process/test_data/pelican-bird.webp
pelican/plugins/image_process/test_data/results/blur/alpha-borders.png
pelican/plugins/image_process/test_data/results/blur/black-borders.png
pelican/plugins/image_process/test_data/results/blur/pelican-bird.png
pelican/plugins/image_process/test_data/results/contour/alpha-borders.png
pelican/plugins/image_process/test_data/results/contour/black-borders.png
pelican/plugins/image_process/test_data/results/contour/pelican-bird.png
pelican/plugins/image_process/test_data/results/crop/alpha-borders.png
pelican/plugins/image_process/test_data/results/crop/black-borders.png
pelican/plugins/image_process/test_data/results/crop/pelican-bird.png
pelican/plugins/image_process/test_data/results/detail/alpha-borders.png
pelican/plugins/image_process/test_data/results/detail/black-borders.png
pelican/plugins/image_process/test_data/results/detail/pelican-bird.png
pelican/plugins/image_process/test_data/results/edge_enhance/alpha-borders.png
pelican/plugins/image_process/test_data/results/edge_enhance/black-borders.png
pelican/plugins/image_process/test_data/results/edge_enhance/pelican-bird.png
pelican/plugins/image_process/test_data/results/edge_enhance_more/alpha-borders.png
pelican_image_process-3.3.0.dist-info/METADATA
pelican_image_process-3.3.0.dist-info/WHEEL
pelican_image_process-3.3.0.dist-info/entry_points.txt
pelican_image_process-3.3.0.dist-info/licenses/LICENSE
pelican_image_process-3.3.0.dist-info/RECORD
