Metadata-Version: 2.1
Name: pelican-image-process
Version: 3.3.0
Summary: Pelican plugin that automates image processing.
Keywords: pelican,plugin,image,responsive,optimization
Author-Email: Pelican Dev Team <authors@getpelican.com>
License: AGPL-3.0
Classifier: Development Status :: 5 - Production/Stable
Classifier: Environment :: Console
Classifier: Framework :: Pelican
Classifier: Framework :: Pelican :: Plugins
Classifier: Intended Audience :: End Users/Desktop
Classifier: License :: OSI Approved :: GNU Affero General Public License v3
Classifier: Operating System :: OS Independent
Classifier: Programming Language :: Python :: 3
Classifier: Programming Language :: Python :: 3.10
Classifier: Programming Language :: Python :: 3.11
Classifier: Programming Language :: Python :: 3.12
Classifier: Programming Language :: Python :: 3.13
Classifier: Programming Language :: Python :: 3.14
Classifier: Topic :: Internet :: WWW/HTTP
Classifier: Topic :: Multimedia :: Graphics
Classifier: Topic :: Software Development :: Libraries :: Python Modules
Project-URL: Homepage, https://github.com/pelican-plugins/image-process
Project-URL: Issue Tracker, https://github.com/pelican-plugins/image-process/issues
Project-URL: Changelog, https://github.com/pelican-plugins/image-process/blob/main/CHANGELOG.md
Project-URL: Funding, https://donate.getpelican.com/
Requires-Python: >=3.10
Requires-Dist: pelican>=4.5
Requires-Dist: beautifulsoup4>=4.9
Requires-Dist: Pillow>=9.1
Requires-Dist: lxml>=4.6
Provides-Extra: markdown
Requires-Dist: markdown>=3.4; extra == "markdown"
